bunnyq.py
setup.py
bunnyq.egg-info/PKG-INFO
bunnyq.egg-info/SOURCES.txt
bunnyq.egg-info/dependency_links.txt
bunnyq.egg-info/entry_points.txt
bunnyq.egg-info/not-zip-safe
bunnyq.egg-info/requires.txt
bunnyq.egg-info/top_level.txt