Metadata-Version: 1.0
Name: bunnyq
Version: 1.0.1
Summary: A command shell and CLI app for testing/administering RabbitMQ using its RESTful HTTP Management API.
Home-page: http://www.github.com/bkjones/bunnyq
Author: Brian K. Jones
Author-email: bkjones@gmail.com
License: MIT
Download-URL: http://www.github.com/bkjones/bunnyq
Keywords: python http amqp rabbit rabbitmq management
Platform: UNKNOWN
Classifier: Intended Audience :: Developers
Classifier: Intended Audience :: System Administrators
Classifier: License :: OSI Approved :: MIT License
Classifier: Natural Language :: English
Classifier: Operating System :: POSIX
Classifier: Programming Language :: Python
Classifier: Programming Language :: Python :: 2
Classifier: Programming Language :: Python :: 2.6
Classifier: Programming Language :: Python :: 2.7
Classifier: Topic :: Internet :: WWW/HTTP
